{"players":[{"name":"fr4nv1lla","numCardsDonated":300,"numCardsReceived":510,"numDaysMember":69,"numWarParticipated":6,"numWarBattlesPlayed":6,"numWarBattlesWon":5},{"name":"Brauliox","numCardsDonated":1062,"numCardsReceived":400,"numDaysMember":69,"numWarParticipated":7,"numWarBattlesPlayed":8,"numWarBattlesWon":7},{"name":"MUNYI","numCardsDonated":656,"numCardsReceived":360,"numDaysMember":69,"numWarParticipated":6,"numWarBattlesPlayed":6,"numWarBattlesWon":6},{"name":"Adan.","numCardsDonated":391,"numCardsReceived":440,"numDaysMember":69,"numWarParticipated":6,"numWarBattlesPlayed":6,"numWarBattlesWon":6},{"name":"RabotusEnormus","numCardsDonated":267,"numCardsReceived":160,"numDaysMember":69,"numWarParticipated":7,"numWarBattlesPlayed":6,"numWarBattlesWon":3},{"name":"...•<CYRUUS>•..","numCardsDonated":20,"numCardsReceived":80,"numDaysMember":1,"numWarParticipated":0,"numWarBattlesPlayed":0,"numWarBattlesWon":0},{"name":"Cipotus Magnus","numCardsDonated":0,"numCardsReceived":0,"numDaysMember":69,"numWarParticipated":5,"numWarBattlesPlayed":4,"numWarBattlesWon":1},{"name":"Byronman","numCardsDonated":300,"numCardsReceived":440,"numDaysMember":69,"numWarParticipated":6,"numWarBattlesPlayed":5,"numWarBattlesWon":3},{"name":"Maggio™","numCardsDonated":751,"numCardsReceived":520,"numDaysMember":5,"numWarParticipated":0,"numWarBattlesPlayed":0,"numWarBattlesWon":0},{"name":"daveltap","numCardsDonated":726,"numCardsReceived":520,"numDaysMember":69,"numWarParticipated":7,"numWarBattlesPlayed":7,"numWarBattlesWon":4},{"name":"fgf","numCardsDonated":518,"numCardsReceived":520,"numDaysMember":69,"numWarParticipated":6,"numWarBattlesPlayed":6,"numWarBattlesWon":6},{"name":"zeratul","numCardsDonated":206,"numCardsReceived":240,"numDaysMember":44,"numWarParticipated":5,"numWarBattlesPlayed":5,"numWarBattlesWon":5},{"name":"Jesus_58","numCardsDonated":10,"numCardsReceived":40,"numDaysMember":27,"numWarParticipated":3,"numWarBattlesPlayed":3,"numWarBattlesWon":3},{"name":"Sandreta","numCardsDonated":799,"numCardsReceived":400,"numDaysMember":69,"numWarParticipated":7,"numWarBattlesPlayed":7,"numWarBattlesWon":1},{"name":"daragon 3000","numCardsDonated":128,"numCardsReceived":200,"numDaysMember":5,"numWarParticipated":1,"numWarBattlesPlayed":1,"numWarBattlesWon":1},{"name":"poseidonmares","numCardsDonated":218,"numCardsReceived":240,"numDaysMember":69,"numWarParticipated":7,"numWarBattlesPlayed":7,"numWarBattlesWon":5},{"name":"Влад","numCardsDonated":358,"numCardsReceived":440,"numDaysMember":25,"numWarParticipated":0,"numWarBattlesPlayed":0,"numWarBattlesWon":0},{"name":"Marturulu","numCardsDonated":58,"numCardsReceived":40,"numDaysMember":69,"numWarParticipated":0,"numWarBattlesPlayed":0,"numWarBattlesWon":0},{"name":"Photon","numCardsDonated":396,"numCardsReceived":400,"numDaysMember":47,"numWarParticipated":7,"numWarBattlesPlayed":7,"numWarBattlesWon":4},{"name":"Player 249","numCardsDonated":1260,"numCardsReceived":540,"numDaysMember":69,"numWarParticipated":4,"numWarBattlesPlayed":4,"numWarBattlesWon":2},{"name":"Muntz","numCardsDonated":0,"numCardsReceived":0,"numDaysMember":27,"numWarParticipated":1,"numWarBattlesPlayed":0,"numWarBattlesWon":0},{"name":"teresa","numCardsDonated":344,"numCardsReceived":520,"numDaysMember":69,"numWarParticipated":6,"numWarBattlesPlayed":6,"numWarBattlesWon":3},{"name":"thorodrim","numCardsDonated":96,"numCardsReceived":400,"numDaysMember":69,"numWarParticipated":7,"numWarBattlesPlayed":7,"numWarBattlesWon":3},{"name":"carloss","numCardsDonated":175,"numCardsReceived":240,"numDaysMember":3,"numWarParticipated":1,"numWarBattlesPlayed":1,"numWarBattlesWon":1},{"name":"macadamien","numCardsDonated":null,"numCardsReceived":null,"numDaysMember":0,"numWarParticipated":0,"numWarBattlesPlayed":0,"numWarBattlesWon":0},{"name":"blanca","numCardsDonated":128,"numCardsReceived":80,"numDaysMember":1,"numWarParticipated":0,"numWarBattlesPlayed":0,"numWarBattlesWon":0},{"name":"Maestro Arnau","numCardsDonated":40,"numCardsReceived":0,"numDaysMember":69,"numWarParticipated":7,"numWarBattlesPlayed":6,"numWarBattlesWon":3},{"name":"JOS3LU","numCardsDonated":48,"numCardsReceived":440,"numDaysMember":10,"numWarParticipated":4,"numWarBattlesPlayed":4,"numWarBattlesWon":2},{"name":"Hugo","numCardsDonated":38,"numCardsReceived":80,"numDaysMember":1,"numWarParticipated":0,"numWarBattlesPlayed":0,"numWarBattlesWon":0},{"name":"AndreaNiki❤️","numCardsDonated":18,"numCardsReceived":0,"numDaysMember":69,"numWarParticipated":0,"numWarBattlesPlayed":0,"numWarBattlesWon":0},{"name":"SubeCopas3000","numCardsDonated":58,"numCardsReceived":200,"numDaysMember":5,"numWarParticipated":1,"numWarBattlesPlayed":2,"numWarBattlesWon":0},{"name":"Akela","numCardsDonated":186,"numCardsReceived":160,"numDaysMember":69,"numWarParticipated":7,"numWarBattlesPlayed":6,"numWarBattlesWon":4},{"name":"AlExViL","numCardsDonated":126,"numCardsReceived":280,"numDaysMember":13,"numWarParticipated":3,"numWarBattlesPlayed":3,"numWarBattlesWon":2},{"name":"rico","numCardsDonated":0,"numCardsReceived":0,"numDaysMember":69,"numWarParticipated":0,"numWarBattlesPlayed":0,"numWarBattlesWon":0},{"name":"ivany","numCardsDonated":30,"numCardsReceived":144,"numDaysMember":14,"numWarParticipated":5,"numWarBattlesPlayed":5,"numWarBattlesWon":2},{"name":"tato2005","numCardsDonated":38,"numCardsReceived":40,"numDaysMember":1,"numWarParticipated":0,"numWarBattlesPlayed":0,"numWarBattlesWon":0},{"name":"Dominal","numCardsDonated":318,"numCardsReceived":400,"numDaysMember":22,"numWarParticipated":6,"numWarBattlesPlayed":6,"numWarBattlesWon":3},{"name":"Somm","numCardsDonated":0,"numCardsReceived":40,"numDaysMember":1,"numWarParticipated":0,"numWarBattlesPlayed":0,"numWarBattlesWon":0},{"name":"ark20","numCardsDonated":80,"numCardsReceived":200,"numDaysMember":5,"numWarParticipated":1,"numWarBattlesPlayed":1,"numWarBattlesWon":0},{"name":"Josefu","numCardsDonated":0,"numCardsReceived":0,"numDaysMember":1,"numWarParticipated":0,"numWarBattlesPlayed":0,"numWarBattlesWon":0},{"name":"canija","numCardsDonated":221,"numCardsReceived":240,"numDaysMember":69,"numWarParticipated":0,"numWarBattlesPlayed":0,"numWarBattlesWon":0},{"name":"XproRaulGM5X","numCardsDonated":64,"numCardsReceived":0,"numDaysMember":1,"numWarParticipated":0,"numWarBattlesPlayed":0,"numWarBattlesWon":0},{"name":"oscar","numCardsDonated":66,"numCardsReceived":400,"numDaysMember":69,"numWarParticipated":7,"numWarBattlesPlayed":6,"numWarBattlesWon":2},{"name":"the killer","numCardsDonated":0,"numCardsReceived":0,"numDaysMember":69,"numWarParticipated":0,"numWarBattlesPlayed":0,"numWarBattlesWon":0},{"name":"diegogar00","numCardsDonated":0,"numCardsReceived":40,"numDaysMember":1,"numWarParticipated":0,"numWarBattlesPlayed":0,"numWarBattlesWon":0},{"name":"Данил","numCardsDonated":144,"numCardsReceived":80,"numDaysMember":56,"numWarParticipated":5,"numWarBattlesPlayed":2,"numWarBattlesWon":1},{"name":"SKA","numCardsDonated":0,"numCardsReceived":0,"numDaysMember":69,"numWarParticipated":0,"numWarBattlesPlayed":0,"numWarBattlesWon":0},{"name":"juanra","numCardsDonated":190,"numCardsReceived":480,"numDaysMember":69,"numWarParticipated":7,"numWarBattlesPlayed":6,"numWarBattlesWon":3},{"name":"polli","numCardsDonated":0,"numCardsReceived":0,"numDaysMember":69,"numWarParticipated":0,"numWarBattlesPlayed":0,"numWarBattlesWon":0},{"name":"riconil","numCardsDonated":447,"numCardsReceived":270,"numDaysMember":11,"numWarParticipated":0,"numWarBattlesPlayed":0,"numWarBattlesWon":0}],"generationDate":1544309826800}