{"players":[{"name":"fr4nv1lla","numCardsDonated":267,"numCardsReceived":840,"numDaysMember":10,"numWarParticipated":6,"numWarBattlesPlayed":7,"numWarBattlesWon":6},{"name":"MUNYI","numCardsDonated":919,"numCardsReceived":560,"numDaysMember":10,"numWarParticipated":5,"numWarBattlesPlayed":5,"numWarBattlesWon":3},{"name":"Brauliox","numCardsDonated":1175,"numCardsReceived":640,"numDaysMember":10,"numWarParticipated":7,"numWarBattlesPlayed":7,"numWarBattlesWon":4},{"name":"Byronman","numCardsDonated":763,"numCardsReceived":760,"numDaysMember":10,"numWarParticipated":6,"numWarBattlesPlayed":6,"numWarBattlesWon":2},{"name":"RabotusEnormus","numCardsDonated":683,"numCardsReceived":520,"numDaysMember":10,"numWarParticipated":7,"numWarBattlesPlayed":6,"numWarBattlesWon":2},{"name":"Adan.","numCardsDonated":452,"numCardsReceived":640,"numDaysMember":10,"numWarParticipated":5,"numWarBattlesPlayed":7,"numWarBattlesWon":5},{"name":"rico","numCardsDonated":904,"numCardsReceived":640,"numDaysMember":10,"numWarParticipated":7,"numWarBattlesPlayed":7,"numWarBattlesWon":2},{"name":"Sandreta","numCardsDonated":891,"numCardsReceived":590,"numDaysMember":10,"numWarParticipated":7,"numWarBattlesPlayed":7,"numWarBattlesWon":4},{"name":"fgf","numCardsDonated":612,"numCardsReceived":840,"numDaysMember":10,"numWarParticipated":7,"numWarBattlesPlayed":7,"numWarBattlesWon":2},{"name":"Cipotus Magnus","numCardsDonated":898,"numCardsReceived":720,"numDaysMember":10,"numWarParticipated":7,"numWarBattlesPlayed":8,"numWarBattlesWon":4},{"name":"teresa","numCardsDonated":752,"numCardsReceived":800,"numDaysMember":10,"numWarParticipated":7,"numWarBattlesPlayed":7,"numWarBattlesWon":4},{"name":"daveltap","numCardsDonated":960,"numCardsReceived":870,"numDaysMember":10,"numWarParticipated":7,"numWarBattlesPlayed":7,"numWarBattlesWon":2},{"name":"poseidonmares","numCardsDonated":30,"numCardsReceived":240,"numDaysMember":10,"numWarParticipated":6,"numWarBattlesPlayed":6,"numWarBattlesWon":4},{"name":"AndreaNiki❤️","numCardsDonated":308,"numCardsReceived":560,"numDaysMember":10,"numWarParticipated":1,"numWarBattlesPlayed":1,"numWarBattlesWon":1},{"name":"errpablito14","numCardsDonated":334,"numCardsReceived":449,"numDaysMember":10,"numWarParticipated":5,"numWarBattlesPlayed":4,"numWarBattlesWon":3},{"name":"Ivensito","numCardsDonated":337,"numCardsReceived":120,"numDaysMember":10,"numWarParticipated":4,"numWarBattlesPlayed":3,"numWarBattlesWon":2},{"name":"SerLex113","numCardsDonated":198,"numCardsReceived":80,"numDaysMember":1,"numWarParticipated":0,"numWarBattlesPlayed":0,"numWarBattlesWon":0},{"name":"Akela","numCardsDonated":474,"numCardsReceived":350,"numDaysMember":10,"numWarParticipated":4,"numWarBattlesPlayed":3,"numWarBattlesWon":2},{"name":"Marturulu","numCardsDonated":209,"numCardsReceived":160,"numDaysMember":10,"numWarParticipated":2,"numWarBattlesPlayed":3,"numWarBattlesWon":0},{"name":"Nuha","numCardsDonated":299,"numCardsReceived":560,"numDaysMember":10,"numWarParticipated":3,"numWarBattlesPlayed":3,"numWarBattlesWon":1},{"name":"Maestro Arnau","numCardsDonated":54,"numCardsReceived":0,"numDaysMember":10,"numWarParticipated":5,"numWarBattlesPlayed":4,"numWarBattlesWon":0},{"name":"the killer","numCardsDonated":0,"numCardsReceived":0,"numDaysMember":10,"numWarParticipated":0,"numWarBattlesPlayed":0,"numWarBattlesWon":0},{"name":"Iagopadin","numCardsDonated":90,"numCardsReceived":40,"numDaysMember":10,"numWarParticipated":4,"numWarBattlesPlayed":4,"numWarBattlesWon":2},{"name":"Víctor e te 200","numCardsDonated":80,"numCardsReceived":40,"numDaysMember":10,"numWarParticipated":0,"numWarBattlesPlayed":0,"numWarBattlesWon":0},{"name":"lucifer","numCardsDonated":164,"numCardsReceived":480,"numDaysMember":10,"numWarParticipated":6,"numWarBattlesPlayed":6,"numWarBattlesWon":0},{"name":"xXHackcrisXx","numCardsDonated":316,"numCardsReceived":520,"numDaysMember":10,"numWarParticipated":0,"numWarBattlesPlayed":0,"numWarBattlesWon":0},{"name":"canija","numCardsDonated":180,"numCardsReceived":240,"numDaysMember":10,"numWarParticipated":2,"numWarBattlesPlayed":1,"numWarBattlesWon":1},{"name":"Player 249","numCardsDonated":1673,"numCardsReceived":920,"numDaysMember":10,"numWarParticipated":4,"numWarBattlesPlayed":4,"numWarBattlesWon":2},{"name":"pj","numCardsDonated":null,"numCardsReceived":null,"numDaysMember":0,"numWarParticipated":0,"numWarBattlesPlayed":0,"numWarBattlesWon":0},{"name":"ilias99","numCardsDonated":null,"numCardsReceived":null,"numDaysMember":0,"numWarParticipated":0,"numWarBattlesPlayed":0,"numWarBattlesWon":0},{"name":"oscar","numCardsDonated":172,"numCardsReceived":520,"numDaysMember":10,"numWarParticipated":7,"numWarBattlesPlayed":7,"numWarBattlesWon":3},{"name":"joelpati88","numCardsDonated":0,"numCardsReceived":0,"numDaysMember":1,"numWarParticipated":0,"numWarBattlesPlayed":0,"numWarBattlesWon":0},{"name":"juanra","numCardsDonated":290,"numCardsReceived":430,"numDaysMember":10,"numWarParticipated":5,"numWarBattlesPlayed":5,"numWarBattlesWon":5},{"name":"SKA","numCardsDonated":122,"numCardsReceived":160,"numDaysMember":10,"numWarParticipated":5,"numWarBattlesPlayed":3,"numWarBattlesWon":0},{"name":"Alex.C","numCardsDonated":529,"numCardsReceived":600,"numDaysMember":7,"numWarParticipated":3,"numWarBattlesPlayed":3,"numWarBattlesWon":0},{"name":"polli","numCardsDonated":0,"numCardsReceived":0,"numDaysMember":10,"numWarParticipated":0,"numWarBattlesPlayed":0,"numWarBattlesWon":0},{"name":"Cris&Hector","numCardsDonated":62,"numCardsReceived":120,"numDaysMember":2,"numWarParticipated":0,"numWarBattlesPlayed":0,"numWarBattlesWon":0},{"name":"♣guillermo♣","numCardsDonated":0,"numCardsReceived":80,"numDaysMember":2,"numWarParticipated":0,"numWarBattlesPlayed":0,"numWarBattlesWon":0},{"name":"jabier","numCardsDonated":172,"numCardsReceived":280,"numDaysMember":10,"numWarParticipated":2,"numWarBattlesPlayed":1,"numWarBattlesWon":0},{"name":"ikito","numCardsDonated":0,"numCardsReceived":0,"numDaysMember":1,"numWarParticipated":0,"numWarBattlesPlayed":0,"numWarBattlesWon":0},{"name":"hamele","numCardsDonated":134,"numCardsReceived":80,"numDaysMember":1,"numWarParticipated":0,"numWarBattlesPlayed":0,"numWarBattlesWon":0},{"name":"Miguel Ángel","numCardsDonated":90,"numCardsReceived":120,"numDaysMember":2,"numWarParticipated":0,"numWarBattlesPlayed":0,"numWarBattlesWon":0},{"name":"ØSÇÅR","numCardsDonated":20,"numCardsReceived":0,"numDaysMember":2,"numWarParticipated":0,"numWarBattlesPlayed":0,"numWarBattlesWon":0},{"name":"hermanos pros","numCardsDonated":44,"numCardsReceived":80,"numDaysMember":3,"numWarParticipated":1,"numWarBattlesPlayed":1,"numWarBattlesWon":1},{"name":"cesi","numCardsDonated":114,"numCardsReceived":76,"numDaysMember":2,"numWarParticipated":0,"numWarBattlesPlayed":0,"numWarBattlesWon":0},{"name":"listo pan","numCardsDonated":76,"numCardsReceived":60,"numDaysMember":2,"numWarParticipated":0,"numWarBattlesPlayed":0,"numWarBattlesWon":0},{"name":"Juan Ruiz","numCardsDonated":20,"numCardsReceived":150,"numDaysMember":2,"numWarParticipated":0,"numWarBattlesPlayed":0,"numWarBattlesWon":0},{"name":"Navarret02","numCardsDonated":60,"numCardsReceived":30,"numDaysMember":3,"numWarParticipated":0,"numWarBattlesPlayed":0,"numWarBattlesWon":0},{"name":"~Leah~","numCardsDonated":0,"numCardsReceived":0,"numDaysMember":2,"numWarParticipated":0,"numWarBattlesPlayed":0,"numWarBattlesWon":0},{"name":"Arnau06","numCardsDonated":0,"numCardsReceived":0,"numDaysMember":10,"numWarParticipated":0,"numWarBattlesPlayed":0,"numWarBattlesWon":0}],"generationDate":1539208681537}