{"players":[{"name":"fr4nv1lla","numCardsDonated":444,"numCardsReceived":880,"numDaysMember":81,"numWarParticipated":7,"numWarBattlesPlayed":7,"numWarBattlesWon":3},{"name":"MUNYI","numCardsDonated":995,"numCardsReceived":610,"numDaysMember":81,"numWarParticipated":7,"numWarBattlesPlayed":7,"numWarBattlesWon":7},{"name":"Brauliox","numCardsDonated":1248,"numCardsReceived":680,"numDaysMember":81,"numWarParticipated":7,"numWarBattlesPlayed":7,"numWarBattlesWon":7},{"name":"fgf","numCardsDonated":730,"numCardsReceived":760,"numDaysMember":81,"numWarParticipated":7,"numWarBattlesPlayed":7,"numWarBattlesWon":3},{"name":"Sandreta","numCardsDonated":645,"numCardsReceived":600,"numDaysMember":81,"numWarParticipated":7,"numWarBattlesPlayed":7,"numWarBattlesWon":4},{"name":"Adan.","numCardsDonated":276,"numCardsReceived":410,"numDaysMember":81,"numWarParticipated":4,"numWarBattlesPlayed":5,"numWarBattlesWon":5},{"name":"teresa","numCardsDonated":597,"numCardsReceived":690,"numDaysMember":81,"numWarParticipated":7,"numWarBattlesPlayed":7,"numWarBattlesWon":5},{"name":"thorodrim","numCardsDonated":64,"numCardsReceived":650,"numDaysMember":81,"numWarParticipated":7,"numWarBattlesPlayed":7,"numWarBattlesWon":2},{"name":"RabotusEnormus","numCardsDonated":84,"numCardsReceived":120,"numDaysMember":81,"numWarParticipated":2,"numWarBattlesPlayed":0,"numWarBattlesWon":0},{"name":"daragon 3000","numCardsDonated":98,"numCardsReceived":200,"numDaysMember":17,"numWarParticipated":3,"numWarBattlesPlayed":3,"numWarBattlesWon":3},{"name":"danipozo","numCardsDonated":168,"numCardsReceived":170,"numDaysMember":4,"numWarParticipated":0,"numWarBattlesPlayed":0,"numWarBattlesWon":0},{"name":"Byronman","numCardsDonated":176,"numCardsReceived":510,"numDaysMember":81,"numWarParticipated":6,"numWarBattlesPlayed":6,"numWarBattlesWon":3},{"name":"...•<CYRUUS>•..","numCardsDonated":693,"numCardsReceived":520,"numDaysMember":13,"numWarParticipated":5,"numWarBattlesPlayed":5,"numWarBattlesWon":4},{"name":"Dominal","numCardsDonated":968,"numCardsReceived":640,"numDaysMember":34,"numWarParticipated":7,"numWarBattlesPlayed":6,"numWarBattlesWon":2},{"name":"Cipotus Magnus","numCardsDonated":0,"numCardsReceived":0,"numDaysMember":81,"numWarParticipated":0,"numWarBattlesPlayed":0,"numWarBattlesWon":0},{"name":"daveltap","numCardsDonated":1076,"numCardsReceived":840,"numDaysMember":81,"numWarParticipated":7,"numWarBattlesPlayed":7,"numWarBattlesWon":4},{"name":"manco javi","numCardsDonated":388,"numCardsReceived":480,"numDaysMember":9,"numWarParticipated":0,"numWarBattlesPlayed":0,"numWarBattlesWon":0},{"name":"zeratul","numCardsDonated":323,"numCardsReceived":360,"numDaysMember":56,"numWarParticipated":6,"numWarBattlesPlayed":6,"numWarBattlesWon":5},{"name":"Carletto","numCardsDonated":857,"numCardsReceived":640,"numDaysMember":11,"numWarParticipated":3,"numWarBattlesPlayed":3,"numWarBattlesWon":1},{"name":"MIQUEL","numCardsDonated":56,"numCardsReceived":80,"numDaysMember":1,"numWarParticipated":0,"numWarBattlesPlayed":0,"numWarBattlesWon":0},{"name":"Marturulu","numCardsDonated":86,"numCardsReceived":120,"numDaysMember":81,"numWarParticipated":1,"numWarBattlesPlayed":1,"numWarBattlesWon":0},{"name":"jose santo","numCardsDonated":141,"numCardsReceived":360,"numDaysMember":9,"numWarParticipated":3,"numWarBattlesPlayed":3,"numWarBattlesWon":2},{"name":"AurHe","numCardsDonated":148,"numCardsReceived":160,"numDaysMember":5,"numWarParticipated":1,"numWarBattlesPlayed":1,"numWarBattlesWon":1},{"name":"Muntz","numCardsDonated":0,"numCardsReceived":0,"numDaysMember":39,"numWarParticipated":0,"numWarBattlesPlayed":0,"numWarBattlesWon":0},{"name":"Влад","numCardsDonated":326,"numCardsReceived":360,"numDaysMember":37,"numWarParticipated":3,"numWarBattlesPlayed":3,"numWarBattlesWon":2},{"name":"david₩","numCardsDonated":120,"numCardsReceived":160,"numDaysMember":10,"numWarParticipated":4,"numWarBattlesPlayed":4,"numWarBattlesWon":3},{"name":"carloss","numCardsDonated":682,"numCardsReceived":520,"numDaysMember":15,"numWarParticipated":7,"numWarBattlesPlayed":7,"numWarBattlesWon":6},{"name":"Hugo","numCardsDonated":452,"numCardsReceived":480,"numDaysMember":13,"numWarParticipated":5,"numWarBattlesPlayed":5,"numWarBattlesWon":1},{"name":"poseidonmares","numCardsDonated":79,"numCardsReceived":400,"numDaysMember":81,"numWarParticipated":7,"numWarBattlesPlayed":7,"numWarBattlesWon":2},{"name":"AGV","numCardsDonated":0,"numCardsReceived":0,"numDaysMember":2,"numWarParticipated":0,"numWarBattlesPlayed":0,"numWarBattlesWon":0},{"name":"Photon","numCardsDonated":284,"numCardsReceived":480,"numDaysMember":59,"numWarParticipated":6,"numWarBattlesPlayed":6,"numWarBattlesWon":4},{"name":"Akela","numCardsDonated":418,"numCardsReceived":400,"numDaysMember":81,"numWarParticipated":7,"numWarBattlesPlayed":7,"numWarBattlesWon":2},{"name":"JOS3LU","numCardsDonated":64,"numCardsReceived":640,"numDaysMember":22,"numWarParticipated":7,"numWarBattlesPlayed":7,"numWarBattlesWon":5},{"name":"TheBoss","numCardsDonated":0,"numCardsReceived":80,"numDaysMember":2,"numWarParticipated":0,"numWarBattlesPlayed":0,"numWarBattlesWon":0},{"name":"Gelin04","numCardsDonated":0,"numCardsReceived":0,"numDaysMember":5,"numWarParticipated":0,"numWarBattlesPlayed":0,"numWarBattlesWon":0},{"name":"AndreaNiki❤️","numCardsDonated":10,"numCardsReceived":80,"numDaysMember":81,"numWarParticipated":0,"numWarBattlesPlayed":0,"numWarBattlesWon":0},{"name":"ivany","numCardsDonated":11,"numCardsReceived":120,"numDaysMember":26,"numWarParticipated":6,"numWarBattlesPlayed":6,"numWarBattlesWon":0},{"name":"Player 249","numCardsDonated":2528,"numCardsReceived":920,"numDaysMember":81,"numWarParticipated":6,"numWarBattlesPlayed":6,"numWarBattlesWon":4},{"name":"ℛℐᏦℐᏆℛᎾℕ","numCardsDonated":null,"numCardsReceived":null,"numDaysMember":0,"numWarParticipated":0,"numWarBattlesPlayed":0,"numWarBattlesWon":0},{"name":"rico","numCardsDonated":0,"numCardsReceived":0,"numDaysMember":81,"numWarParticipated":0,"numWarBattlesPlayed":0,"numWarBattlesWon":0},{"name":"canija","numCardsDonated":210,"numCardsReceived":240,"numDaysMember":81,"numWarParticipated":0,"numWarBattlesPlayed":0,"numWarBattlesWon":0},{"name":"Somm","numCardsDonated":92,"numCardsReceived":160,"numDaysMember":13,"numWarParticipated":2,"numWarBattlesPlayed":2,"numWarBattlesWon":0},{"name":"Maestro Arnau","numCardsDonated":37,"numCardsReceived":0,"numDaysMember":81,"numWarParticipated":7,"numWarBattlesPlayed":7,"numWarBattlesWon":2},{"name":"Josefu","numCardsDonated":158,"numCardsReceived":160,"numDaysMember":13,"numWarParticipated":4,"numWarBattlesPlayed":4,"numWarBattlesWon":1},{"name":"the killer","numCardsDonated":0,"numCardsReceived":160,"numDaysMember":81,"numWarParticipated":0,"numWarBattlesPlayed":0,"numWarBattlesWon":0},{"name":"oscar","numCardsDonated":90,"numCardsReceived":560,"numDaysMember":81,"numWarParticipated":7,"numWarBattlesPlayed":8,"numWarBattlesWon":3},{"name":"SKA","numCardsDonated":0,"numCardsReceived":0,"numDaysMember":81,"numWarParticipated":0,"numWarBattlesPlayed":0,"numWarBattlesWon":0},{"name":"juanra","numCardsDonated":418,"numCardsReceived":680,"numDaysMember":81,"numWarParticipated":7,"numWarBattlesPlayed":8,"numWarBattlesWon":3},{"name":"riconil","numCardsDonated":924,"numCardsReceived":680,"numDaysMember":23,"numWarParticipated":5,"numWarBattlesPlayed":5,"numWarBattlesWon":1},{"name":"polli","numCardsDonated":0,"numCardsReceived":0,"numDaysMember":81,"numWarParticipated":0,"numWarBattlesPlayed":0,"numWarBattlesWon":0}],"generationDate":1545346621418}